platrock/Common/BounceModels.py
platrock/Common/ColorPalettes.py
platrock/Common/Debug.py
platrock/Common/Math.cpython-312-x86_64-linux-gnu.so
platrock/Common/Math.py
platrock/Common/Objects.py
platrock/Common/Outputs.py
platrock/Common/Projects.py
platrock/Common/PyUtils.py
platrock/Common/RasterTools.py
platrock/Common/RetroCompatibility.py
platrock/Common/ShapeSimulations.py
platrock/Common/Simulations.py
platrock/Common/ThreeDObjects.py
platrock/Common/ThreeDPostprocessings.py
platrock/Common/ThreeDSimulations.py
platrock/Common/ThreeDToolbox.cpython-312-x86_64-linux-gnu.so
platrock/Common/TimeSteppedSimulations.py
platrock/Common/TreesGenerators.py
platrock/Common/TwoDObjects.py
platrock/Common/TwoDSimulations.py
platrock/Common/Utils.py
platrock/Common/__init__.py
platrock/Cython/Math.pyx
platrock/Cython/ThreeDToolbox.pyx
platrock/GUI/Plot2D.py
platrock/GUI/Plot3D.py
platrock/GUI/View3D.py
platrock/GUI/__init__.py
platrock/ThreeD/Engines.py
platrock/ThreeD/Objects.py
platrock/ThreeD/Simulations.py
platrock/ThreeD/__init__.py
platrock/ThreeDShape/Objects.py
platrock/ThreeDShape/Simulations.py
platrock/ThreeDShape/__init__.py
platrock/TwoD/Geoms.py
platrock/TwoD/Objects.py
platrock/TwoD/Simulations.py
platrock/TwoD/__init__.py
platrock/TwoDShape/Objects.py
platrock/TwoDShape/Simulations.py
platrock/TwoDShape/__init__.py
platrock/__init__.py
platrock/__main__.py
platrock-0.4.6.dist-info/LICENSE
platrock-0.4.6.dist-info/METADATA
platrock-0.4.6.dist-info/WHEEL
platrock-0.4.6.dist-info/entry_points.txt
platrock-0.4.6.dist-info/RECORD
