Metadata-Version: 2.1
Name: platrock
Version: 0.4.6
Summary: Scientific multi-model software for the numerical simulation of rockfalls.
Home-page: http://platrock.org/
License: GPL-3.0-only
Keywords: rockfall,scientific,modeling
Author: Francois Kneib
Author-email: francois.kneib@gmail.com
Requires-Python: >=3.10,<4.0
Classifier: License :: OSI Approved :: GNU General Public License v3 (GPLv3)
Classifier: Operating System :: Unix
Classifier: Programming Language :: Python :: 3
Classifier: Programming Language :: Python :: 3.10
Classifier: Programming Language :: Python :: 3.11
Classifier: Programming Language :: Python :: 3.12
Requires-Dist: descartes (>=1.1.0,<2.0.0)
Requires-Dist: fasteners (>=0.19,<0.20)
Requires-Dist: h5py (>=3.11.0,<4.0.0)
Requires-Dist: ipython (>=8.27.0,<9.0.0)
Requires-Dist: jsonpickle (>=3.3.0,<4.0.0)
Requires-Dist: matplotlib (>=3.9.2,<4.0.0)
Requires-Dist: numba (>=0.60.0,<0.61.0)
Requires-Dist: numpy (<2.1)
Requires-Dist: numpy-quaternion (>=2023.0.4,<2024.0.0)
Requires-Dist: numpy-stl (>=3.1.2,<4.0.0)
Requires-Dist: plotly (>=5.24.1,<6.0.0)
Requires-Dist: psutil (>=6.0.0,<7.0.0)
Requires-Dist: requests (>=2.32.3,<3.0.0)
Requires-Dist: scikit-image (>=0.24.0,<0.25.0)
Requires-Dist: scipy (>=1.14.1,<2.0.0)
Requires-Dist: shapely (>=2.0.6,<3.0.0)
Requires-Dist: yappi (>=1.6.0,<2.0.0)
Project-URL: Repository, https://gitlab.com/platrock/platrock
